{"nodes": [{"id": "documentspage", "label": "DocumentsPage.tsx", "file_type": "code", "source_file": "frontend/src/pages/DocumentsPage.tsx", "source_location": "L1"}], "edges": [{"source": "documentspage", "target": "react", "relation": "imports_from", "confidence": "EXTRACTED", "source_file": "frontend/src/pages/DocumentsPage.tsx", "source_location": "L1", "weight": 1.0}, {"source": "documentspage", "target": "antd", "relation": "imports_from", "confidence": "EXTRACTED", "source_file": "frontend/src/pages/DocumentsPage.tsx", "source_location": "L2", "weight": 1.0}, {"source": "documentspage", "target": "uploadpanel", "relation": "imports_from", "confidence": "EXTRACTED", "source_file": "frontend/src/pages/DocumentsPage.tsx", "source_location": "L3", "weight": 1.0}, {"source": "documentspage", "target": "documentlist", "relation": "imports_from", "confidence": "EXTRACTED", "source_file": "frontend/src/pages/DocumentsPage.tsx", "source_location": "L4", "weight": 1.0}, {"source": "documentspage", "target": "searchtestpanel", "relation": "imports_from", "confidence": "EXTRACTED", "source_file": "frontend/src/pages/DocumentsPage.tsx", "source_location": "L5", "weight": 1.0}, {"source": "documentspage", "target": "documentstore", "relation": "imports_from", "confidence": "EXTRACTED", "source_file": "frontend/src/pages/DocumentsPage.tsx", "source_location": "L6", "weight": 1.0}]}